MANIFEST.in
README.rst
setup.cfg
setup.py
bin/eatiht
eatiht/__init__.py
eatiht/eatiht.py
eatiht/eatiht_trees.py
eatiht/etv2.py
eatiht/v2.py
eatiht.egg-info/PKG-INFO
eatiht.egg-info/SOURCES.txt
eatiht.egg-info/dependency_links.txt
eatiht.egg-info/not-zip-safe
eatiht.egg-info/requires.txt
eatiht.egg-info/top_level.txt
eatiht/tests/assets/__init__.py
eatiht/tests/assets/__init__.pyc
eatiht/tests/assets/foo1.html
eatiht/tests/assets/full_of_foos.html
eatiht/tests/assets/google_wiki.html
eatiht/tests/assets/regex_dot_endings.html
eatiht/tests/assets/regex_various_endings.html